odoo/addons/repair_type/README.rst
odoo/addons/repair_type/__init__.py
odoo/addons/repair_type/__manifest__.py
odoo/addons/repair_type/i18n/es.po
odoo/addons/repair_type/i18n/hr.po
odoo/addons/repair_type/i18n/it.po
odoo/addons/repair_type/i18n/repair_type.pot
odoo/addons/repair_type/models/__init__.py
odoo/addons/repair_type/models/stock_move.py
odoo/addons/repair_type/models/stock_picking_type.py
odoo/addons/repair_type/readme/CONTRIBUTORS.md
odoo/addons/repair_type/readme/DESCRIPTION.md
odoo/addons/repair_type/readme/USAGE.md
odoo/addons/repair_type/static/description/icon.png
odoo/addons/repair_type/static/description/index.html
odoo/addons/repair_type/tests/__init__.py
odoo/addons/repair_type/tests/test_repair_type.py
odoo/addons/repair_type/views/stock_picking_type_views.xml
odoo_addon_repair_type-18.0.1.0.1.dist-info/METADATA
odoo_addon_repair_type-18.0.1.0.1.dist-info/WHEEL
odoo_addon_repair_type-18.0.1.0.1.dist-info/top_level.txt
odoo_addon_repair_type-18.0.1.0.1.dist-info/RECORD
